resume_json/__init__.py
resume_json/__main__.py
resume_json/basic_tui.py
resume_json/json_resume.py
resume_json/resume_cli.py
resume_json/resume_export.py
resume_json/resume_init.py
resume_json/resume_serve.py
resume_json/resume_validate.py
resume_json/template_generator.py
resume_json/templates/cora.html
resume_json/templates/even.html
resume_json/templates/macchiato.html
resume_json/templates/short.html
resume_json/templates/stackoverflow.html
resume_json_cli-0.3.0.dist-info/LICENSE
resume_json_cli-0.3.0.dist-info/METADATA
resume_json_cli-0.3.0.dist-info/WHEEL
resume_json_cli-0.3.0.dist-info/entry_points.txt
resume_json_cli-0.3.0.dist-info/top_level.txt
resume_json_cli-0.3.0.dist-info/RECORD
