Metadata-Version: 2.1
Name: resume-json-cli
Version: 0.3.0
Summary: A project to work with resume json
Home-page: https://github.com/moshe742/resume-json-python
Maintainer: Moshe Nahmias
Maintainer-email: moshegrey@gmail.com
License: UNKNOWN
Project-URL: bug_tracker, https://github.com/moshe742/resume-json-python/issues
Platform: UNKNOWN
Classifier: Environment :: Console
Classifier: License :: OSI Approved :: MIT License
Classifier: Topic :: Utilities
Requires-Python: >=3.6
Requires-Dist: Jinja2
Requires-Dist: jsonschema
Requires-Dist: requests
Requires-Dist: WeasyPrint
Requires-Dist: cherrypy
